{"type": "FeatureCollection", "model": "gadm0", "features": [{"type": "Feature", "geometry": {"type": "Point", "coordinates": [29.472954, 26.87729]}, "properties": {"id": "EGY"}}, {"type": "Feature", "geometry": {"type": "Point", "coordinates": [34.680547, -18.64375]}, "properties": {"id": "MOZ"}}, {"type": "Feature", "geometry": {"type": "Point", "coordinates": [105.452446, 46.837115]}, "properties": {"id": "MNG"}}, {"type": "Feature", "geometry": {"type": "Point", "coordinates": [-110.448606, 56.836445]}, "properties": {"id": "CAN"}}, {"type": "Feature", "geometry": {"type": "Point", "coordinates": [145.619582, 14.99107]}, "properties": {"id": "MNP"}}, {"type": "Feature", "geometry": {"type": "Point", "coordinates": [20.645733, 6.60929]}, "properties": {"id": "CAF"}}, {"type": "Feature", "geometry": {"type": "Point", "coordinates": [12.675159, 64.55008]}, "properties": {"id": "NOR"}}, {"type": "Feature", "geometry": {"type": "Point", "coordinates": [95.860855, 19.26451]}, "properties": {"id": "MMR"}}, {"type": "Feature", "geometry": {"type": "Point", "coordinates": [125.243657, 7.681805]}, "properties": {"id": "PHL"}}, {"type": "Feature", "geometry": {"type": "Point", "coordinates": [45.151143, -12.791595]}, "properties": {"id": "MYT"}}, {"type": "Feature", "geometry": {"type": "Point", "coordinates": [33.760564, -13.284375]}, "properties": {"id": "MWI"}}, {"type": "Feature", "geometry": {"type": "Point", "coordinates": [27.529638, 64.94891]}, "properties": {"id": "FIN"}}, {"type": "Feature", "geometry": {"type": "Point", "coordinates": [2.195853, 46.703915]}, "properties": {"id": "FRA"}}, {"type": "Feature", "geometry": {"type": "Point", "coordinates": [0.603086, 28.059095]}, "properties": {"id": "DZA"}}, {"type": "Feature", "geometry": {"type": "Point", "coordinates": [22.696878, 79.83833]}, "properties": {"id": "SJM"}}, {"type": "Feature", "geometry": {"type": "Point", "coordinates": [144.758153, 13.4543]}, "properties": {"id": "GUM"}}, {"type": "Feature", "geometry": {"type": "Point", "coordinates": [19.847774, 60.196094]}, "properties": {"id": "ALA"}}, {"type": "Feature", "geometry": {"type": "Point", "coordinates": [-61.676757, 12.102495]}, "properties": {"id": "GRD"}}, {"type": "Feature", "geometry": {"type": "Point", "coordinates": [21.959088, 39.06305]}, "properties": {"id": "GRC"}}, {"type": "Feature", "geometry": {"type": "Point", "coordinates": [160.127491, -9.575625]}, "properties": {"id": "SLB"}}, {"type": "Feature", "geometry": {"type": "Point", "coordinates": [-40.355306, 71.801515]}, "properties": {"id": "GRL"}}, {"type": "Feature", "geometry": {"type": "Point", "coordinates": [70.136967, 30.298885]}, "properties": {"id": "PAK"}}, {"type": "Feature", "geometry": {"type": "Point", "coordinates": [88.380897, 59.464505]}, "properties": {"id": "RUS"}}, {"type": "Feature", "geometry": {"type": "Point", "coordinates": [12.45337, 43.941655]}, "properties": {"id": "SMR"}}, {"type": "Feature", "geometry": {"type": "Point", "coordinates": [-62.748524, 17.313055]}, "properties": {"id": "KNA"}}, {"type": "Feature", "geometry": {"type": "Point", "coordinates": [-87.208509, 14.51684]}, "properties": {"id": "HND"}}, {"type": "Feature", "geometry": {"type": "Point", "coordinates": [101.685835, 13.034375]}, "properties": {"id": "THA"}}, {"type": "Feature", "geometry": {"type": "Point", "coordinates": [14.883466, 62.17244]}, "properties": {"id": "SWE"}}, {"type": "Feature", "geometry": {"type": "Point", "coordinates": [35.49876, 38.946515]}, "properties": {"id": "TUR"}}, {"type": "Feature", "geometry": {"type": "Point", "coordinates": [-63.075399, 18.21069]}, "properties": {"id": "AIA"}}, {"type": "Feature", "geometry": {"type": "Point", "coordinates": [57.730228, 38.96555]}, "properties": {"id": "TKM"}}, {"type": "Feature", "geometry": {"type": "Point", "coordinates": [-61.245939, 10.44069]}, "properties": {"id": "TTO"}}, {"type": "Feature", "geometry": {"type": "Point", "coordinates": [-175.24814, -21.168055]}, "properties": {"id": "TON"}}, {"type": "Feature", "geometry": {"type": "Point", "coordinates": [-170.737528, -14.31153]}, "properties": {"id": "ASM"}}, {"type": "Feature", "geometry": {"type": "Point", "coordinates": [-62.189097, 16.739855]}, "properties": {"id": "MSR"}}, {"type": "Feature", "geometry": {"type": "Point", "coordinates": [9.555549, 47.15972]}, "properties": {"id": "LIE"}}, {"type": "Feature", "geometry": {"type": "Point", "coordinates": [168.700808, 7.314095]}, "properties": {"id": "MHL"}}, {"type": "Feature", "geometry": {"type": "Point", "coordinates": [19.163636, 51.929535]}, "properties": {"id": "POL"}}, {"type": "Feature", "geometry": {"type": "Point", "coordinates": [-3.495106, 39.872355]}, "properties": {"id": "ESP"}}, {"type": "Feature", "geometry": {"type": "Point", "coordinates": [34.226597, -6.368195]}, "properties": {"id": "TZA"}}, {"type": "Feature", "geometry": {"type": "Point", "coordinates": [33.896121, 48.38447]}, "properties": {"id": "UKR"}}, {"type": "Feature", "geometry": {"type": "Point", "coordinates": [-171.852046, -9.20038]}, "properties": {"id": "TKL"}}, {"type": "Feature", "geometry": {"type": "Point", "coordinates": [33.395215, 35.165965]}, "properties": {"id": "CYP"}}, {"type": "Feature", "geometry": {"type": "Point", "coordinates": [-65.440685, 6.471145]}, "properties": {"id": "VEN"}}, {"type": "Feature", "geometry": {"type": "Point", "coordinates": [107.86532, 15.9334]}, "properties": {"id": "VNM"}}, {"type": "Feature", "geometry": {"type": "Point", "coordinates": [63.403005, 41.378945]}, "properties": {"id": "UZB"}}, {"type": "Feature", "geometry": {"type": "Point", "coordinates": [-99.661494, 37.241465]}, "properties": {"id": "USA"}}, {"type": "Feature", "geometry": {"type": "Point", "coordinates": [-64.624914, 18.41743]}, "properties": {"id": "VGB"}}, {"type": "Feature", "geometry": {"type": "Point", "coordinates": [51.132293, 25.316525]}, "properties": {"id": "QAT"}}, {"type": "Feature", "geometry": {"type": "Point", "coordinates": [79.926654, 20.62297]}, "properties": {"id": "IND"}}, {"type": "Feature", "geometry": {"type": "Point", "coordinates": [15.350488, 44.744405]}, "properties": {"id": "HRV"}}, {"type": "Feature", "geometry": {"type": "Point", "coordinates": [-62.811944, 17.904452]}, "properties": {"id": "BLM"}}, {"type": "Feature", "geometry": {"type": "Point", "coordinates": [-66.390953, 18.21805]}, "properties": {"id": "PRI"}}, {"type": "Feature", "geometry": {"type": "Point", "coordinates": [46.723462, -18.780835]}, "properties": {"id": "MDG"}}, {"type": "Feature", "geometry": {"type": "Point", "coordinates": [18.876846, -11.909165]}, "properties": {"id": "AGO"}}, {"type": "Feature", "geometry": {"type": "Point", "coordinates": [65.20012, 33.939675]}, "properties": {"id": "AFG"}}, {"type": "Feature", "geometry": {"type": "Point", "coordinates": [54.10207, 32.42201]}, "properties": {"id": "IRN"}}, {"type": "Feature", "geometry": {"type": "Point", "coordinates": [12.683175, 42.49868]}, "properties": {"id": "ITA"}}, {"type": "Feature", "geometry": {"type": "Point", "coordinates": [113.319434, 0.089585]}, "properties": {"id": "IDN"}}, {"type": "Feature", "geometry": {"type": "Point", "coordinates": [-7.967921, 53.4125]}, "properties": {"id": "IRL"}}, {"type": "Feature", "geometry": {"type": "Point", "coordinates": [-18.618669, 64.95659]}, "properties": {"id": "ISL"}}, {"type": "Feature", "geometry": {"type": "Point", "coordinates": [-13.689145, 24.266525]}, "properties": {"id": "ESH"}}, {"type": "Feature", "geometry": {"type": "Point", "coordinates": [9.314264, 55.94312]}, "properties": {"id": "DNK"}}, {"type": "Feature", "geometry": {"type": "Point", "coordinates": [89.864204, 23.68562]}, "properties": {"id": "BGD"}}, {"type": "Feature", "geometry": {"type": "Point", "coordinates": [-102.264998, 23.638405]}, "properties": {"id": "MEX"}}, {"type": "Feature", "geometry": {"type": "Point", "coordinates": [-71.495939, -35.703375]}, "properties": {"id": "CHL"}}, {"type": "Feature", "geometry": {"type": "Point", "coordinates": [-72.594246, 4.11882]}, "properties": {"id": "COL"}}, {"type": "Feature", "geometry": {"type": "Point", "coordinates": [22.452232, -4.038125]}, "properties": {"id": "COD"}}, {"type": "Feature", "geometry": {"type": "Point", "coordinates": [-77.944987, 21.497465]}, "properties": {"id": "CUB"}}, {"type": "Feature", "geometry": {"type": "Point", "coordinates": [10.479821, 1.646875]}, "properties": {"id": "GNQ"}}, {"type": "Feature", "geometry": {"type": "Point", "coordinates": [-70.116253, 18.764165]}, "properties": {"id": "DOM"}}, {"type": "Feature", "geometry": {"type": "Point", "coordinates": [-8.288582, 39.564575]}, "properties": {"id": "PRT"}}, {"type": "Feature", "geometry": {"type": "Point", "coordinates": [176.617003, -38.02271]}, "properties": {"id": "NZL"}}, {"type": "Feature", "geometry": {"type": "Point", "coordinates": [-63.956432, -37.034865]}, "properties": {"id": "ARG"}}, {"type": "Feature", "geometry": {"type": "Point", "coordinates": [34.386931, 31.432915]}, "properties": {"id": "PSE"}}, {"type": "Feature", "geometry": {"type": "Point", "coordinates": [10.547971, 51.172595]}, "properties": {"id": "DEU"}}, {"type": "Feature", "geometry": {"type": "Point", "coordinates": [102.101782, 3.989375]}, "properties": {"id": "MYS"}}, {"type": "Feature", "geometry": {"type": "Point", "coordinates": [-68.245926, 12.16625]}, "properties": {"id": "BES"}}, {"type": "Feature", "geometry": {"type": "Point", "coordinates": [-2.126458, 49.214822]}, "properties": {"id": "JEY"}}, {"type": "Feature", "geometry": {"type": "Point", "coordinates": [-88.721809, 17.211945]}, "properties": {"id": "BLZ"}}, {"type": "Feature", "geometry": {"type": "Point", "coordinates": [75.084578, 41.21682]}, "properties": {"id": "KGZ"}}, {"type": "Feature", "geometry": {"type": "Point", "coordinates": [66.353362, 48.033605]}, "properties": {"id": "KAZ"}}, {"type": "Feature", "geometry": {"type": "Point", "coordinates": [143.336017, 43.47338]}, "properties": {"id": "JPN"}}, {"type": "Feature", "geometry": {"type": "Point", "coordinates": [-60.966855, 13.936385]}, "properties": {"id": "LCA"}}, {"type": "Feature", "geometry": {"type": "Point", "coordinates": [103.815482, 1.343335]}, "properties": {"id": "SGP"}}, {"type": "Feature", "geometry": {"type": "Point", "coordinates": [-171.752043, -13.94847]}, "properties": {"id": "WSM"}}, {"type": "Feature", "geometry": {"type": "Point", "coordinates": [17.224018, 26.27868]}, "properties": {"id": "LBY"}}, {"type": "Feature", "geometry": {"type": "Point", "coordinates": [104.69354, 18.212215]}, "properties": {"id": "LAO"}}, {"type": "Feature", "geometry": {"type": "Point", "coordinates": [-61.197334, 13.26167]}, "properties": {"id": "VCT"}}, {"type": "Feature", "geometry": {"type": "Point", "coordinates": [70.949127, 38.87247]}, "properties": {"id": "TJK"}}, {"type": "Feature", "geometry": {"type": "Point", "coordinates": [-178.135288, -14.283612]}, "properties": {"id": "WLF"}}, {"type": "Feature", "geometry": {"type": "Point", "coordinates": [55.145825, 24.35111]}, "properties": {"id": "ARE"}}, {"type": "Feature", "geometry": {"type": "Point", "coordinates": [-73.335068, 21.11833]}, "properties": {"id": "BHS"}}, {"type": "Feature", "geometry": {"type": "Point", "coordinates": [26.134255, -28.474925]}, "properties": {"id": "ZAF"}}, {"type": "Feature", "geometry": {"type": "Point", "coordinates": [-0.731025, 17.49604]}, "properties": {"id": "MLI"}}, {"type": "Feature", "geometry": {"type": "Point", "coordinates": [13.592733, 7.339445]}, "properties": {"id": "CMR"}}, {"type": "Feature", "geometry": {"type": "Point", "coordinates": [24.120396, 55.168395]}, "properties": {"id": "LTU"}}, {"type": "Feature", "geometry": {"type": "Point", "coordinates": [179.21988, -8.51921]}, "properties": {"id": "TUV"}}, {"type": "Feature", "geometry": {"type": "Point", "coordinates": [-85.568315, 12.864445]}, "properties": {"id": "NIC"}}, {"type": "Feature", "geometry": {"type": "Point", "coordinates": [29.970463, -1.939165]}, "properties": {"id": "RWA"}}, {"type": "Feature", "geometry": {"type": "Point", "coordinates": [16.083099, -0.64479]}, "properties": {"id": "COG"}}, {"type": "Feature", "geometry": {"type": "Point", "coordinates": [42.516076, 33.229125]}, "properties": {"id": "IRQ"}}, {"type": "Feature", "geometry": {"type": "Point", "coordinates": [31.463026, -26.520905]}, "properties": {"id": "SWZ"}}, {"type": "Feature", "geometry": {"type": "Point", "coordinates": [-78.291106, -1.83792]}, "properties": {"id": "ECU"}}, {"type": "Feature", "geometry": {"type": "Point", "coordinates": [-2.581439, 49.462778]}, "properties": {"id": "GGY"}}, {"type": "Feature", "geometry": {"type": "Point", "coordinates": [1.581566, 42.553225]}, "properties": {"id": "AND"}}, {"type": "Feature", "geometry": {"type": "Point", "coordinates": [144.365651, -6.644585]}, "properties": {"id": "PNG"}}, {"type": "Feature", "geometry": {"type": "Point", "coordinates": [5.506818, 52.09561]}, "properties": {"id": "NLD"}}, {"type": "Feature", "geometry": {"type": "Point", "coordinates": [133.056911, -24.9125]}, "properties": {"id": "AUS"}}, {"type": "Feature", "geometry": {"type": "Point", "coordinates": [8.455281, 46.810445]}, "properties": {"id": "CHE"}}, {"type": "Feature", "geometry": {"type": "Point", "coordinates": [-4.51486, 54.236528]}, "properties": {"id": "IMN"}}, {"type": "Feature", "geometry": {"type": "Point", "coordinates": [17.251084, -22.943545]}, "properties": {"id": "NAM"}}, {"type": "Feature", "geometry": {"type": "Point", "coordinates": [-0.868102, 60.759056]}, "properties": {"id": "NA"}}, {"type": "Feature", "geometry": {"type": "Point", "coordinates": [9.894738, 17.679025]}, "properties": {"id": "NER"}}, {"type": "Feature", "geometry": {"type": "Point", "coordinates": [-72.258749, 18.992495]}, "properties": {"id": "HTI"}}, {"type": "Feature", "geometry": {"type": "Point", "coordinates": [127.965167, 36.441445]}, "properties": {"id": "KOR"}}, {"type": "Feature", "geometry": {"type": "Point", "coordinates": [125.766996, -8.88208]}, "properties": {"id": "TLS"}}, {"type": "Feature", "geometry": {"type": "Point", "coordinates": [166.920297, -0.53274]}, "properties": {"id": "NRU"}}, {"type": "Feature", "geometry": {"type": "Point", "coordinates": [-61.330024, 15.386665]}, "properties": {"id": "DMA"}}, {"type": "Feature", "geometry": {"type": "Point", "coordinates": [43.648683, 42.295545]}, "properties": {"id": "GEO"}}, {"type": "Feature", "geometry": {"type": "Point", "coordinates": [158.22871, 6.890415]}, "properties": {"id": "FSM"}}, {"type": "Feature", "geometry": {"type": "Point", "coordinates": [-61.669831, 16.229265]}, "properties": {"id": "GLP"}}, {"type": "Feature", "geometry": {"type": "Point", "coordinates": [47.4781, 15.795]}, "properties": {"id": "YEM"}}, {"type": "Feature", "geometry": {"type": "Point", "coordinates": [6.602856, 0.21132]}, "properties": {"id": "STP"}}, {"type": "Feature", "geometry": {"type": "Point", "coordinates": [-64.747235, 17.739165]}, "properties": {"id": "VIR"}}, {"type": "Feature", "geometry": {"type": "Point", "coordinates": [-75.761877, -9.196805]}, "properties": {"id": "PER"}}, {"type": "Feature", "geometry": {"type": "Point", "coordinates": [44.633791, 24.265445]}, "properties": {"id": "SAU"}}, {"type": "Feature", "geometry": {"type": "Point", "coordinates": [25.43823, -13.095595]}, "properties": {"id": "ZMB"}}, {"type": "Feature", "geometry": {"type": "Point", "coordinates": [20.913141, 42.543957]}, "properties": {"id": "XKO"}}, {"type": "Feature", "geometry": {"type": "Point", "coordinates": [-12.282129, -37.112728]}, "properties": {"id": "SHN"}}, {"type": "Feature", "geometry": {"type": "Point", "coordinates": [-56.196381, 46.781111]}, "properties": {"id": "SPM"}}, {"type": "Feature", "geometry": {"type": "Point", "coordinates": [70.227295, -49.18691]}, "properties": {"id": "ATF"}}, {"type": "Feature", "geometry": {"type": "Point", "coordinates": [-49.726803, -14.244795]}, "properties": {"id": "BRA"}}, {"type": "Feature", "geometry": {"type": "Point", "coordinates": [33.766486, 35.030756]}, "properties": {"id": "XAD"}}, {"type": "Feature", "geometry": {"type": "Point", "coordinates": [-160.017533, -0.378201]}, "properties": {"id": "UMI"}}, {"type": "Feature", "geometry": {"type": "Point", "coordinates": [33.828592, 35.35014]}, "properties": {"id": "ZNC"}}, {"type": "Feature", "geometry": {"type": "Point", "coordinates": [14.630551, 46.156245]}, "properties": {"id": "SVN"}}, {"type": "Feature", "geometry": {"type": "Point", "coordinates": [28.186219, -29.600105]}, "properties": {"id": "LSO"}}, {"type": "Feature", "geometry": {"type": "Point", "coordinates": [38.087548, 15.178475]}, "properties": {"id": "ERI"}}, {"type": "Feature", "geometry": {"type": "Point", "coordinates": [35.85905, 33.855305]}, "properties": {"id": "LBN"}}, {"type": "Feature", "geometry": {"type": "Point", "coordinates": [165.238914, -21.23641]}, "properties": {"id": "NCL"}}, {"type": "Feature", "geometry": {"type": "Point", "coordinates": [-81.204296, 19.309235]}, "properties": {"id": "CYM"}}, {"type": "Feature", "geometry": {"type": "Point", "coordinates": [90.342828, 27.516735]}, "properties": {"id": "BTN"}}, {"type": "Feature", "geometry": {"type": "Point", "coordinates": [55.51954, -21.11014]}, "properties": {"id": "REU"}}, {"type": "Feature", "geometry": {"type": "Point", "coordinates": [98.637366, 36.901765]}, "properties": {"id": "CHN"}}, {"type": "Feature", "geometry": {"type": "Point", "coordinates": [-53.042943, 3.9475]}, "properties": {"id": "GUF"}}, {"type": "Feature", "geometry": {"type": "Point", "coordinates": [134.583056, 7.543195]}, "properties": {"id": "PLW"}}, {"type": "Feature", "geometry": {"type": "Point", "coordinates": [38.973099, 9.171665]}, "properties": {"id": "ETH"}}, {"type": "Feature", "geometry": {"type": "Point", "coordinates": [114.513449, 4.55222]}, "properties": {"id": "BRN"}}, {"type": "Feature", "geometry": {"type": "Point", "coordinates": [24.456798, 56.89645]}, "properties": {"id": "LVA"}}, {"type": "Feature", "geometry": {"type": "Point", "coordinates": [-90.300534, 15.80764]}, "properties": {"id": "GTM"}}, {"type": "Feature", "geometry": {"type": "Point", "coordinates": [-64.734744, 32.316245]}, "properties": {"id": "BMU"}}, {"type": "Feature", "geometry": {"type": "Point", "coordinates": [-139.012517, -9.783335]}, "properties": {"id": "PYF"}}, {"type": "Feature", "geometry": {"type": "Point", "coordinates": [19.27768, 42.69754]}, "properties": {"id": "MNE"}}, {"type": "Feature", "geometry": {"type": "Point", "coordinates": [-64.228233, -16.28723]}, "properties": {"id": "BOL"}}, {"type": "Feature", "geometry": {"type": "Point", "coordinates": [-1.915957, 54.311665]}, "properties": {"id": "GBR"}}, {"type": "Feature", "geometry": {"type": "Point", "coordinates": [38.56188, 34.82867]}, "properties": {"id": "SYR"}}, {"type": "Feature", "geometry": {"type": "Point", "coordinates": [47.395328, 29.291975]}, "properties": {"id": "KWT"}}, {"type": "Feature", "geometry": {"type": "Point", "coordinates": [36.318067, 31.317815]}, "properties": {"id": "JOR"}}, {"type": "Feature", "geometry": {"type": "Point", "coordinates": [-25.18408, 17.050275]}, "properties": {"id": "CPV"}}, {"type": "Feature", "geometry": {"type": "Point", "coordinates": [50.548585, 26.01375]}, "properties": {"id": "BHR"}}, {"type": "Feature", "geometry": {"type": "Point", "coordinates": [-59.573608, 13.19868]}, "properties": {"id": "BRB"}}, {"type": "Feature", "geometry": {"type": "Point", "coordinates": [168.362741, -17.673745]}, "properties": {"id": "VUT"}}, {"type": "Feature", "geometry": {"type": "Point", "coordinates": [7.960368, 9.08611]}, "properties": {"id": "NGA"}}, {"type": "Feature", "geometry": {"type": "Point", "coordinates": [-14.366188, 11.804305]}, "properties": {"id": "GNB"}}, {"type": "Feature", "geometry": {"type": "Point", "coordinates": [-61.779028, 17.06583]}, "properties": {"id": "ATG"}}, {"type": "Feature", "geometry": {"type": "Point", "coordinates": [42.523162, 11.835]}, "properties": {"id": "DJI"}}, {"type": "Feature", "geometry": {"type": "Point", "coordinates": [-88.902957, 13.80402]}, "properties": {"id": "SLV"}}, {"type": "Feature", "geometry": {"type": "Point", "coordinates": [25.170339, 42.748815]}, "properties": {"id": "BGR"}}, {"type": "Feature", "geometry": {"type": "Point", "coordinates": [21.735667, 41.616665]}, "properties": {"id": "MKD"}}, {"type": "Feature", "geometry": {"type": "Point", "coordinates": [-56.122925, 3.92354]}, "properties": {"id": "SUR"}}, {"type": "Feature", "geometry": {"type": "Point", "coordinates": [-83.644525, 9.61833]}, "properties": {"id": "CRI"}}, {"type": "Feature", "geometry": {"type": "Point", "coordinates": [57.582446, -20.25792]}, "properties": {"id": "MUS"}}, {"type": "Feature", "geometry": {"type": "Point", "coordinates": [-6.371109, 31.7875]}, "properties": {"id": "MAR"}}, {"type": "Feature", "geometry": {"type": "Point", "coordinates": [14.429851, 35.91014]}, "properties": {"id": "MLT"}}, {"type": "Feature", "geometry": {"type": "Point", "coordinates": [25.484072, 58.63194]}, "properties": {"id": "EST"}}, {"type": "Feature", "geometry": {"type": "Point", "coordinates": [14.761616, 47.7118]}, "properties": {"id": "AUT"}}, {"type": "Feature", "geometry": {"type": "Point", "coordinates": [20.030633, 41.127975]}, "properties": {"id": "ALB"}}, {"type": "Feature", "geometry": {"type": "Point", "coordinates": [-61.004167, 14.62361]}, "properties": {"id": "MTQ"}}, {"type": "Feature", "geometry": {"type": "Point", "coordinates": [29.130545, 7.85942]}, "properties": {"id": "SSD"}}, {"type": "Feature", "geometry": {"type": "Point", "coordinates": [19.623563, 48.653185]}, "properties": {"id": "SVK"}}, {"type": "Feature", "geometry": {"type": "Point", "coordinates": [-14.330684, 13.44201]}, "properties": {"id": "GMB"}}, {"type": "Feature", "geometry": {"type": "Point", "coordinates": [-14.659258, 14.49597]}, "properties": {"id": "SEN"}}, {"type": "Feature", "geometry": {"type": "Point", "coordinates": [24.480885, -22.34719]}, "properties": {"id": "BWA"}}, {"type": "Feature", "geometry": {"type": "Point", "coordinates": [18.560369, 15.43948]}, "properties": {"id": "TCD"}}, {"type": "Feature", "geometry": {"type": "Point", "coordinates": [-1.078863, 7.919825]}, "properties": {"id": "GHA"}}, {"type": "Feature", "geometry": {"type": "Point", "coordinates": [46.846534, 5.227915]}, "properties": {"id": "SOM"}}, {"type": "Feature", "geometry": {"type": "Point", "coordinates": [4.918146, 50.50409]}, "properties": {"id": "BEL"}}, {"type": "Feature", "geometry": {"type": "Point", "coordinates": [34.635405, 31.378675]}, "properties": {"id": "ISR"}}, {"type": "Feature", "geometry": {"type": "Point", "coordinates": [80.671276, 7.87333]}, "properties": {"id": "LKA"}}, {"type": "Feature", "geometry": {"type": "Point", "coordinates": [-9.654893, 9.940035]}, "properties": {"id": "GIN"}}, {"type": "Feature", "geometry": {"type": "Point", "coordinates": [32.691251, 1.364305]}, "properties": {"id": "UGA"}}, {"type": "Feature", "geometry": {"type": "Point", "coordinates": [-11.881094, 8.46479]}, "properties": {"id": "SLE"}}, {"type": "Feature", "geometry": {"type": "Point", "coordinates": [177.992865, -17.798335]}, "properties": {"id": "FJI"}}, {"type": "Feature", "geometry": {"type": "Point", "coordinates": [126.795639, 40.349505]}, "properties": {"id": "PRK"}}, {"type": "Feature", "geometry": {"type": "Point", "coordinates": [-5.687959, 7.538215]}, "properties": {"id": "CIV"}}, {"type": "Feature", "geometry": {"type": "Point", "coordinates": [17.95115, 43.935555]}, "properties": {"id": "BIH"}}, {"type": "Feature", "geometry": {"type": "Point", "coordinates": [28.832696, 46.96485]}, "properties": {"id": "MDA"}}, {"type": "Feature", "geometry": {"type": "Point", "coordinates": [15.547982, 49.862285]}, "properties": {"id": "CZE"}}, {"type": "Feature", "geometry": {"type": "Point", "coordinates": [-6.81054, 62.210965]}, "properties": {"id": "FRO"}}, {"type": "Feature", "geometry": {"type": "Point", "coordinates": [44.847985, 40.07464]}, "properties": {"id": "ARM"}}, {"type": "Feature", "geometry": {"type": "Point", "coordinates": [55.478917, -4.67382]}, "properties": {"id": "SYC"}}, {"type": "Feature", "geometry": {"type": "Point", "coordinates": [24.282645, 45.944015]}, "properties": {"id": "ROU"}}, {"type": "Feature", "geometry": {"type": "Point", "coordinates": [28.042757, 53.697495]}, "properties": {"id": "BLR"}}, {"type": "Feature", "geometry": {"type": "Point", "coordinates": [29.781318, 15.45097]}, "properties": {"id": "SDN"}}, {"type": "Feature", "geometry": {"type": "Point", "coordinates": [83.084703, 28.39944]}, "properties": {"id": "NPL"}}, {"type": "Feature", "geometry": {"type": "Point", "coordinates": [-159.789328, -21.21278]}, "properties": {"id": "COK"}}, {"type": "Feature", "geometry": {"type": "Point", "coordinates": [120.81498, 23.592985]}, "properties": {"id": "TWN"}}, {"type": "Feature", "geometry": {"type": "Point", "coordinates": [-58.935186, 4.89167]}, "properties": {"id": "GUY"}}, {"type": "Feature", "geometry": {"type": "Point", "coordinates": [11.743205, -0.785]}, "properties": {"id": "GAB"}}, {"type": "Feature", "geometry": {"type": "Point", "coordinates": [8.869514, 33.78888]}, "properties": {"id": "TUN"}}, {"type": "Feature", "geometry": {"type": "Point", "coordinates": [29.347786, -19.00814]}, "properties": {"id": "ZWE"}}, {"type": "Feature", "geometry": {"type": "Point", "coordinates": [-9.640426, 6.42611]}, "properties": {"id": "LBR"}}, {"type": "Feature", "geometry": {"type": "Point", "coordinates": [1.033338, 8.64305]}, "properties": {"id": "TGO"}}, {"type": "Feature", "geometry": {"type": "Point", "coordinates": [56.993483, 20.80375]}, "properties": {"id": "OMN"}}, {"type": "Feature", "geometry": {"type": "Point", "coordinates": [21.023956, 44.01518]}, "properties": {"id": "SRB"}}, {"type": "Feature", "geometry": {"type": "Point", "coordinates": [-55.819826, -32.5232]}, "properties": {"id": "URY"}}, {"type": "Feature", "geometry": {"type": "Point", "coordinates": [-81.475356, 8.40903]}, "properties": {"id": "PAN"}}, {"type": "Feature", "geometry": {"type": "Point", "coordinates": [2.295524, 9.310905]}, "properties": {"id": "BEN"}}, {"type": "Feature", "geometry": {"type": "Point", "coordinates": [29.929941, -3.37513]}, "properties": {"id": "BDI"}}, {"type": "Feature", "geometry": {"type": "Point", "coordinates": [-58.46622, -23.438615]}, "properties": {"id": "PRY"}}, {"type": "Feature", "geometry": {"type": "Point", "coordinates": [-71.742369, 21.79625]}, "properties": {"id": "TCA"}}, {"type": "Feature", "geometry": {"type": "Point", "coordinates": [-11.470722, 21.01001]}, "properties": {"id": "MRT"}}, {"type": "Feature", "geometry": {"type": "Point", "coordinates": [48.564813, 40.539055]}, "properties": {"id": "AZE"}}, {"type": "Feature", "geometry": {"type": "Point", "coordinates": [105.125652, 12.578675]}, "properties": {"id": "KHM"}}, {"type": "Feature", "geometry": {"type": "Point", "coordinates": [44.428055, -12.241735]}, "properties": {"id": "COM"}}, {"type": "Feature", "geometry": {"type": "Point", "coordinates": [19.135791, 47.172705]}, "properties": {"id": "HUN"}}, {"type": "Feature", "geometry": {"type": "Point", "coordinates": [-1.189886, 12.237915]}, "properties": {"id": "BFA"}}, {"type": "Feature", "geometry": {"type": "Point", "coordinates": [6.075788, 49.814435]}, "properties": {"id": "LUX"}}, {"type": "Feature", "geometry": {"type": "Point", "coordinates": [37.472996, -0.067085]}, "properties": {"id": "KEN"}}, {"type": "Feature", "geometry": {"type": "Point", "coordinates": [-77.160161, 18.118055]}, "properties": {"id": "JAM"}}]}
